{"category":"Pokémon","id":"xy11-18","illustrator":"Shibuzoh.","image":"https://assets.tcgdex.net/fr/xy/xy11/18","localId":"18","name":"Ouisticram","rarity":"Commune","set":{"cardCount":{"official":114,"total":114},"id":"xy11","logo":"https://assets.tcgdex.net/fr/xy/xy11/logo","name":"Offensive Vapeur","symbol":"https://assets.tcgdex.net/univ/xy/xy11/symbol"},"variants":{"firstEdition":false,"holo":false,"normal":true,"reverse":true},"dexId":[390],"hp":60,"types":["Feu"],"stage":"Base","attacks":[{"cost":["Incolore"],"name":"Griffe","damage":10},{"cost":["Feu","Incolore"],"name":"Flammèche","effect":"Lancez une pièce. Si c’est pile, défaussez une Énergie Fire attachée à ce Pokémon.","damage":30}],"weaknesses":[{"type":"Eau","value":"×2"}],"retreat":1,"legal":{"standard":false,"expanded":true}}