{"id":"pl3-122","localId":122,"dexId":111,"name":"Rhinocorne","hp":70,"type":[{"id":4,"name":"Combat"}],"image":{"low":"https://assets.tcgdex.net/fr/pl/pl3/122/low","high":"https://assets.tcgdex.net/fr/pl/pl3/122/high"},"tags":[{"id":0,"name":"Pokémon de base"}],"illustrator":{"id":16,"name":"Tomokazu Komiya"},"attacks":[{"name":"Écrasement","cost":["Incolore","Incolore"],"text":"Lancez une pièce. Si c'est face, cette attaque inflige 10 dégâts plus 20 dégâts supplémentaires.","damage":10},{"name":"Empal'korne","cost":["Combat","Combat","Incolore"],"damage":50}],"weaknesses":[{"type":{"id":10,"name":"Eau"},"value":"+10"}],"resistances":[{"type":{"id":7,"name":"Électrique"},"value":"-20"}],"retreat":2,"rarity":{"id":0,"name":"Commun"},"category":{"id":0,"name":"Pokémon"},"set":{"name":"Supreme Victors","code":"pl3"}}