{"id":"xy7-49","localId":"49","name":"Metagross","image":"https://assets.tcgdex.net/en/xy/xy7/49","illustrator":"kirisAki","rarity":"Rare","category":"Pokemon","variants":{"normal":true,"reverse":true,"holo":false,"firstEdition":false},"set":{"id":"xy7","logo":"https://assets.tcgdex.net/en/xy/xy7/logo","symbol":"https://assets.tcgdex.net/univ/xy/xy7/symbol","name":"Ancient Origins","cardCount":{"total":101,"official":98}},"dexId":[376],"hp":150,"types":["Metal"],"evolveFrom":"Metang","stage":"Stage2","abilities":[{"type":"Ability","name":"Magnetic Warp","effect":"Once during your turn (before your attack), you may switch your Active Pokémon with 1 of your Benched Pokémon. If you do, your opponent switches his or her Active Pokémon with 1 of his or her Benched Pokémon."}],"attacks":[{"cost":["Metal","Metal","Colorless","Colorless"],"name":"Iron Cannon","effect":"You may discard all Metal Energy attached to this Pokémon. If you do, this attack does 80 more damage.","damage":80}],"weaknesses":[{"type":"Fire","value":"×2"}],"resistances":[{"type":"Psychic","value":"-20"}],"retreat":4}