{"id":"dp2-78","localId":"78","name":"Croagunk","image":"https://assets.tcgdex.net/en/dp/dp2/78","illustrator":"Ken Sugimori","rarity":"Common","category":"Pokemon","variants":{"normal":true,"reverse":true,"holo":false,"firstEdition":false},"set":{"id":"dp2","logo":"https://assets.tcgdex.net/en/dp/dp2/logo","symbol":"https://assets.tcgdex.net/univ/dp/dp2/symbol","name":"Mysterious Treasures","cardCount":{"total":124,"official":122}},"dexId":[453],"hp":60,"types":["Psychic"],"stage":"Basic","attacks":[{"cost":["Colorless"],"name":"Ghastly Sound","effect":"Flip a coin. If heads, your opponent can't play any Supporter cards from his or her hand during his or her next turn."},{"cost":["Psychic","Psychic"],"name":"Finger Poke","effect":"Flip a coin. If heads, the Defending Pokémon is now Poisoned.","damage":20}],"weaknesses":[{"type":"Psychic","value":"+10"}]}