{"id":"swsh3.5-47","localId":"47","name":"Duralugon V","image":"https://assets.tcgdex.net/fr/swsh/swsh3.5/47","illustrator":"aky CG Works","rarity":"Rare","category":"Pokémon","variants":{"normal":true,"reverse":true,"holo":false,"firstEdition":false},"set":{"id":"swsh3.5","symbol":"https://assets.tcgdex.net/univ/swsh/swsh3.5/symbol","name":"La Voie du Maître","cardCount":{"total":80,"official":70}},"hp":220,"types":["Métal"],"abilities":[{"type":"Talent","name":"Strate Dure","effect":"Ce Pokémon subit 30 dégâts de moins provenant des attaques (après application de la Faiblesse et de la Résistance)."}],"attacks":[{"cost":["Incolore","Incolore","Incolore"],"name":"Frappe Répétée","effect":"Cette attaque inflige 40 dégâts supplémentaires pour chaque Énergie Metal attachée à ce Pokémon.","damage":"10+"}],"weaknesses":[{"type":"Feu","value":"×2"}],"resistances":[{"type":"Plante","value":"-30"}],"retreat":3,"regulationMark":"D","legal":{"standard":true,"expanded":true}}