{"id":"ex11-31","localId":"31","name":"Sunny Castform","image":"https://assets.tcgdex.net/en/ex/ex11/31","illustrator":"Miki Tanaka","rarity":"Rare","category":"Pokemon","variants":{"normal":true,"reverse":true,"holo":false,"firstEdition":false},"set":{"id":"ex11","logo":"https://assets.tcgdex.net/en/ex/ex11/logo","symbol":"https://assets.tcgdex.net/univ/ex/ex11/symbol","name":"Delta Species","cardCount":{"total":114,"official":113}},"dexId":[351],"hp":70,"types":["Fire"],"stage":"Basic","abilities":[{"type":"Poke-POWER","name":"Temperamental Weather","effect":"Once during your turn (before your attack), you may search your deck for Castform, Rain Castform, or Snow-cloud Castform and switch it with Sunny Castform. (Any cards attached to Sunny Castform, damage counters, Special Conditions, and effects on it are now on the new Pokémon.) Shuffle Sunny Castform back into your deck. You can't use more than 1 Temperamental Weather Poké-Power each turn."}],"attacks":[{"cost":["Colorless","Colorless"],"name":"Holon Search","effect":"Search your deck for a Holon Energy card and attach it to 1 of your Pokémon. Shuffle your deck afterward."}],"weaknesses":[{"type":"Water","value":"×2"}],"legal":{"standard":false,"expanded":false}}