{"id":"bw2-33","localId":"33","name":"Statitik","image":"https://assets.tcgdex.net/fr/bw/bw2/33","illustrator":"Kagemaru Himeno","rarity":"Commune","category":"Pokémon","variants":{"normal":true,"reverse":true,"holo":false,"firstEdition":false},"set":{"id":"bw2","logo":"https://assets.tcgdex.net/fr/bw/bw2/logo","symbol":"https://assets.tcgdex.net/univ/bw/bw2/symbol","name":"Pouvoirs Émergents","cardCount":{"total":98,"official":98}},"dexId":[595],"hp":40,"types":["Électrique"],"stage":"Base","attacks":[{"cost":["Incolore"],"name":"Ronge","damage":10}],"weaknesses":[{"type":"Combat","value":"×2"}],"retreat":1,"legal":{"standard":false,"expanded":true}}