{"id":"swsh1-21","localId":21,"name":"Eldegoss","hp":80,"type":[{"id":6,"name":"Grass"}],"image":{"low":"https://assets.tcgdex.net/en/swsh/swsh1/21/low.png"},"evolveFrom":"Gossifleur","evolveTo":[],"tags":[{"id":14,"name":"Stage 1"}],"illustrator":{"id":13,"name":"Kagemaru Himeno"},"abilities":[],"attacks":[{"name":"Blessing of Fluff","cost":["Colorless"],"text":"Search your deck for up to 3 Grass Energy cards and attach them to your Benched Pokémon in any way you like. Then, shuffle your deck."},{"name":"Leafage","cost":["Grass"],"damage":30}],"weaknesses":[{"type":{"id":5,"name":"Fire"},"value":"×2"}],"resistances":[],"retreat":1,"rarity":{"id":1,"name":"unCommon"},"category":{"id":0,"name":"Pokémon"},"set":{"name":"Sword & Shield","code":"swsh1"}}