{"category":"Pokemon","id":"swsh5-72","illustrator":"ryoma uratsuka","image":"https://assets.tcgdex.net/en/swsh/swsh5/72","localId":"72","name":"Gliscor","rarity":"Uncommon","set":{"cardCount":{"official":202,"total":202},"id":"swsh5","logo":"https://assets.tcgdex.net/en/swsh/swsh5/logo","name":"Battle Styles","symbol":"https://assets.tcgdex.net/univ/swsh/swsh5/symbol"},"variants":{"firstEdition":false,"holo":false,"normal":true,"reverse":true},"hp":120,"types":["Fighting"],"evolveFrom":"Gligar","attacks":[{"cost":["Colorless","Colorless"],"name":"Acrobatics","effect":"Flip 2 coins. This attack does 40 more damage for each heads.","damage":"20+"},{"cost":["Fighting","Colorless","Colorless"],"name":"Guillotine","damage":90}],"weaknesses":[{"type":"Grass","value":"×2"}],"retreat":1,"regulationMark":"E","legal":{"standard":true,"expanded":true}}