{"id":"xy6-57","localId":"57","name":"Salamence","image":"https://assets.tcgdex.net/en/xy/xy6/57","illustrator":"TOKIYA","rarity":"Rare","category":"Pokemon","variants":{"normal":true,"reverse":true,"holo":false,"firstEdition":false},"set":{"id":"xy6","logo":"https://assets.tcgdex.net/en/xy/xy6/logo","symbol":"https://assets.tcgdex.net/univ/xy/xy6/symbol","name":"Roaring Skies","cardCount":{"total":110,"official":108}},"dexId":[373],"hp":160,"types":["Dragon"],"evolveFrom":"Shelgon","stage":"Stage2","attacks":[{"cost":["Fire"],"name":"Shatter","effect":"Discard any Stadium card in play.","damage":60},{"cost":["Water","Colorless","Colorless"],"name":"Power Howl","effect":"This attack does 20 damage times the number of cards in your opponent's hand.","damage":20},{"cost":["Fire","Fire","Water","Colorless"],"name":"Steam Blast","effect":"Discard 3 Energy attached to this Pokémon.","damage":170}],"weaknesses":[{"type":"Fairy","value":"×2"}],"retreat":4}