{"id":"pl1-63","localId":"63","name":"Armulys","image":"https://assets.tcgdex.net/fr/pl/pl1/63","illustrator":"Kyoko Umemoto","rarity":"Non Commune","category":"Pokémon","variants":{"normal":true,"reverse":true,"holo":false,"firstEdition":false},"set":{"id":"pl1","logo":"https://assets.tcgdex.net/fr/pl/pl1/logo","symbol":"https://assets.tcgdex.net/univ/pl/pl1/symbol","name":"Platine","cardCount":{"total":133,"official":127}},"dexId":[266],"hp":80,"types":["Plante"],"evolveFrom":"Chenipotte","stage":"Niveau1","attacks":[{"name":"Ascension","effect":"Choisissez dans votre deck une carte qui évolue d'Armulys et placez-la sur Armulys. (Vous le faites ainsi évoluer.) Ensuite, mélangez votre deck."},{"cost":["Plante","Incolore"],"name":"Ficelle collante","effect":"Lancez une pièce. Si c'est face, le Pokémon Défenseur est maintenant Paralysé.","damage":20}],"weaknesses":[{"type":"Feu","value":"+20"}],"retreat":2}