{"category":"Entrenador","id":"sm7.5-61","illustrator":"kodama","localId":"61","name":"Lance ◇","rarity":"Rara","set":{"cardCount":{"official":70,"total":78},"id":"sm7.5"},"variants":{"firstEdition":false,"holo":false,"normal":true,"reverse":true},"effect":"Puedes jugar esta carta solo si 1 de tus Pokémon quedó Fuera de Combate durante el último turno de tu rival.\n\nBusca en tu baraja hasta 2 Pokémon Dragon y ponlos en tu Banca. Después, baraja las cartas de tu baraja.","trainerType":"Partidario","legal":{"standard":true,"expanded":true}}