{"id":"bw7-91","localId":"91","name":"Léopardus","illustrator":"kawayoo","rarity":"Rare","category":"Pokémon","variants":{"normal":true,"reverse":true,"holo":true,"firstEdition":false},"set":{"id":"bw7","name":"Frontières Franchies","cardCount":{"total":149,"official":149}},"dexId":[510],"hp":80,"types":["Obscurité"],"evolveFrom":"Chacripan","stage":"Niveau1","attacks":[{"cost":["Obscurité"],"name":"Queue Étourdissante","effect":"Le Pokémon Défenseur est maintenant Confus."},{"cost":["Obscurité","Incolore","Incolore"],"name":"Assistance","effect":"Lancez une pièce. Si c'est face, choisissez une attaque de l'un de vos Pokémon de Banc et utilisez-la en tant que cette attaque."}],"weaknesses":[{"type":"Combat","value":"×2"}],"resistances":[{"type":"Psy","value":"-20"}],"retreat":1}