{"id":"sm8-107","localId":"107","name":"Poipole","image":"https://assets.tcgdex.net/en/sm/sm8/107","illustrator":"Hitoshi Ariga","rarity":"Common","category":"Pokemon","variants":{"normal":true,"reverse":true,"holo":true,"firstEdition":false},"set":{"id":"sm8","logo":"https://assets.tcgdex.net/en/sm/sm8/logo","symbol":"https://assets.tcgdex.net/univ/sm/sm8/symbol","name":"Lost Thunder","cardCount":{"total":236,"official":214}},"dexId":[803],"hp":70,"types":["Psychic"],"stage":"Basic","attacks":[{"cost":["Colorless"],"name":"Eye Opener","effect":"Look at your face-down Prize cards."},{"cost":["Colorless","Colorless"],"name":"Peck","damage":20}],"weaknesses":[{"type":"Psychic","value":"×2"}],"retreat":1}