{"category":"Pokémon","id":"sm4-69","illustrator":"Kagemaru Himeno","localId":"69","name":"Escavalier","rarity":"Rara","set":{"cardCount":{"official":111,"total":124},"id":"sm4","symbol":"https://assets.tcgdex.net/univ/sm/sm4/symbol"},"variants":{"firstEdition":false,"holo":false,"normal":true,"reverse":true},"dexId":[589],"hp":120,"types":["Metálica"],"stage":"Fase 1","attacks":[{"cost":["Metálica"],"name":"Ataque Furia","effect":"Lanza 3 monedas. Este ataque hace 30 puntos de daño por cada cara.","damage":"30×"},{"cost":["Metálica","Metálica","Incolora"],"name":"Bloqueo de Hierro","effect":"Este Pokémon se hace 30 puntos de daño a sí mismo.","damage":130}],"weaknesses":[{"type":"Guego","value":"×2"}],"resistances":[{"type":"Psíquico","value":"-20"}],"retreat":2,"legal":{"standard":true,"expanded":true}}