{"id":"sm12-57","localId":57,"dexId":489,"name":"Phione","hp":70,"type":[{"id":10,"name":"Water"}],"image":{"low":"https://assets.tcgdex.net/en/sm/sm12/57/low","high":"https://assets.tcgdex.net/en/sm/sm12/57/high"},"tags":[{"id":0,"name":"Basic Pokémon"}],"illustrator":{"id":180,"name":"AKIRA EGAWA"},"abilities":[{"name":"Whirlpool Suction","text":"Once during your turn (before your attack), if this Pokémon is on your Bench, you may have your opponent switch their Active Pokémon with 1 of their Benched Pokémon. If you do, discard all cards attached to this Pokémon and put it on the bottom of your deck.","type":{"id":2,"name":"Ability"}}],"attacks":[{"name":"Rain Splash","cost":["Water"],"damage":10}],"weaknesses":[{"type":{"id":6,"name":"Grass"},"value":"×2"}],"retreat":1,"rarity":{"id":3,"name":"Rare"},"category":{"id":0,"name":"Pokémon"},"set":{"name":"Cosmic Eclipse","code":"sm12"}}