{"category":"Pokémon","id":"sm9-44","illustrator":"Akira Komayama","localId":"44","name":"Blitzle","rarity":"Commún","set":{"cardCount":{"official":181,"total":196},"id":"sm9","symbol":"https://assets.tcgdex.net/univ/sm/sm9/symbol"},"variants":{"firstEdition":false,"holo":false,"normal":true,"reverse":true},"dexId":[522],"hp":60,"types":["Rayo"],"stage":"Basico","attacks":[{"cost":["Rayo"],"name":"Entrega Veloz","effect":"Busca en tu baraja hasta 2 cartas de Electropoder, enséñalas y ponlas en tu mano. Después, baraja las cartas de tu baraja."},{"cost":["Rayo","Incolora"],"name":"Electropatada","damage":20}],"weaknesses":[{"type":"Lucha","value":"×2"}],"resistances":[{"type":"Metálica","value":"-20"}],"retreat":1,"legal":{"standard":true,"expanded":true}}