{"id":"bw1-86","localId":"86","name":"Déflaisan","illustrator":"Kagemaru Himeno","rarity":"Rare","category":"Pokémon","variants":{"normal":true,"reverse":true,"holo":true,"firstEdition":false},"set":{"id":"bw1","name":"Noir & Blanc","cardCount":{"total":115,"official":114}},"dexId":[521],"hp":120,"types":["Incolore"],"evolveFrom":"Colombeau","stage":"Biveau2","attacks":[{"cost":["Incolore","Incolore"],"name":"Vol","effect":"Lancez une pièce. Si c’est pile, cette attaque ne fait rien. Si c’est face, évitez tous les effets d’attaques (y compris les dégâts) infligés à ce Pokémon pendant le prochain tour de votre adversaire.","damage":50},{"cost":["Incolore","Incolore","Incolore"],"name":"Vent Glacial","damage":70}],"weaknesses":[{"type":"Électrique","value":"×2"}],"resistances":[{"type":"Combat","value":"-20"}],"retreat":1}