{"id":"ex2-62","localId":"62","name":"Duskull","image":"https://assets.tcgdex.net/en/ex/ex2/62","illustrator":"Aya Kusube","rarity":"Common","category":"Pokemon","variants":{"normal":true,"reverse":true,"holo":true,"firstEdition":false},"set":{"id":"ex2","logo":"https://assets.tcgdex.net/en/ex/ex2/logo","symbol":"https://assets.tcgdex.net/univ/ex/ex2/symbol","name":"Sandstorm","cardCount":{"total":100,"official":100}},"dexId":[355],"hp":40,"types":["Psychic"],"stage":"Basic","attacks":[{"cost":["Psychic"],"name":"Haunt","effect":"Put 1 damage counter on the Defending Pokémon."},{"cost":["Colorless","Colorless"],"name":"Dark Mind","effect":"Does 10 damage to 1 of your opponent's Benched Pokémon. (Don't apply Weakness and Resistance for Benched Pokémon.)","damage":10}],"weaknesses":[{"type":"Darkness","value":"×2"}],"resistances":[{"type":"Fire","value":"-30"}]}