{"category":"Pokemon","id":"swsh1-98","illustrator":"KEIICHIRO ITO","localId":"98","name":"Rizeros","rarity":"Uncommon","set":{"cardCount":{"official":202,"total":216},"id":"swsh1","symbol":"https://assets.tcgdex.net/univ/swsh/swsh1/symbol"},"variants":{"firstEdition":false,"holo":false,"normal":true,"reverse":true},"hp":120,"types":["Fighting"],"stage":"Stage1","attacks":[{"cost":["Fighting","Colorless","Colorless"],"name":"Hornbohrer","damage":50},{"cost":["Fighting","Fighting","Colorless","Colorless"],"name":"Steinhagel","effect":"Diese Attacke fügt auch 2 Pokémon auf der Bank deines Gegners 10 Schadenspunkte zu. (Wende Schwäche und Resistenz bei Pokémon auf der Bank nicht an.)","damage":100}],"weaknesses":[{"type":"Grass","value":"×2"}],"retreat":4,"regulationMark":"D","legal":{"standard":true,"expanded":true}}