{"category":"Pokémon","id":"xy11-74","illustrator":"kirisAki","image":"https://assets.tcgdex.net/fr/xy/xy11/74","localId":"74","name":"Cobaltium","rarity":"Rare","set":{"cardCount":{"official":114,"total":114},"id":"xy11","logo":"https://assets.tcgdex.net/fr/xy/xy11/logo","name":"Offensive Vapeur","symbol":"https://assets.tcgdex.net/univ/xy/xy11/symbol"},"variants":{"firstEdition":false,"holo":false,"normal":true,"reverse":true},"dexId":[638],"hp":120,"types":["Métal"],"stage":"Base","attacks":[{"cost":["Métal"],"name":"Prévention","effect":"Évitez tous les dégâts infligés à ce Pokémon par des attaques de Pokémon de base pendant le prochain tour de votre adversaire. Ce Pokémon ne peut pas utiliser Prévention pendant votre prochain tour."},{"cost":["Métal","Métal"],"name":"Explo-Vengeance","effect":"Cette attaque inflige 30 dégâts supplémentaires pour chaque carte Récompense que votre adversaire a récupérée.","damage":30}],"weaknesses":[{"type":"Feu","value":"×2"}],"resistances":[{"type":"Psy","value":"-20"}],"retreat":2,"legal":{"standard":false,"expanded":true}}