{"category":"Pokemon","id":"dp2-101","illustrator":"Ken Sugimori","image":"https://assets.tcgdex.net/en/dp/dp2/101","localId":"101","name":"Snover","rarity":"Common","set":{"cardCount":{"official":122,"total":124},"id":"dp2","logo":"https://assets.tcgdex.net/en/dp/dp2/logo","name":"Mysterious Treasures","symbol":"https://assets.tcgdex.net/univ/dp/dp2/symbol"},"variants":{"firstEdition":false,"holo":false,"normal":true,"reverse":true},"dexId":[459],"hp":60,"types":["Grass"],"stage":"Basic","attacks":[{"name":"Curiosity","effect":"Look at your opponent's hand."},{"cost":["Water","Colorless"],"name":"Snowball Fight","effect":"Flip a coin. If tails, Snover does 10 damage to itself.","damage":30}],"weaknesses":[{"type":"Fire","value":"+10"}],"legal":{"standard":false,"expanded":false}}