{"category":"Trainer","id":"xy4-108","illustrator":"Toyste Beach","image":"https://assets.tcgdex.net/en/xy/xy4/108","localId":"108","name":"Trick Coin","rarity":"Uncommon","set":{"cardCount":{"official":119,"total":124},"id":"xy4","logo":"https://assets.tcgdex.net/en/xy/xy4/logo","name":"Phantom Forces","symbol":"https://assets.tcgdex.net/univ/xy/xy4/symbol"},"variants":{"firstEdition":false,"holo":false,"normal":true,"reverse":true},"trainerType":"Tool","legal":{"standard":false,"expanded":true}}