{"id":"xy4-75","localId":"75","name":"Mucuscule","image":"https://assets.tcgdex.net/fr/xy/xy4/75","illustrator":"Sanosuke Sakuma","rarity":"Commune","category":"Pokémon","variants":{"normal":true,"reverse":true,"holo":true,"firstEdition":false},"set":{"id":"xy4","name":"Vigueur Spectrale","cardCount":{"total":122,"official":119}},"dexId":[704],"hp":50,"types":["Dragon"],"stage":"Base","attacks":[{"cost":["Incolore"],"name":"Poisseux","effect":"Soignez 10 dégâts à ce Pokémon."},{"cost":["Eau","Fée"],"name":"Charge","damage":20}],"weaknesses":[{"type":"Fée","value":"×2"}],"retreat":2}