{"category":"Energy","id":"swsh2-171","localId":"171","name":"Fang-Energie","rarity":"Uncommon","set":{"cardCount":{"official":192,"total":209},"id":"swsh2","symbol":"https://assets.tcgdex.net/univ/swsh/swsh2/symbol"},"variants":{"firstEdition":false,"holo":false,"normal":true,"reverse":true},"effect":"Solange diese Karte an ein Pokémon angelegt ist, liefert sie Colorless-Energie.\n\nWenn du diese Karte aus deiner Hand an ein Pokémon anlegst, durchsuche dein Deck nach 1 Basis-Pokémon und lege es auf deine Bank. Mische anschließend dein Deck.","energyType":"Special","regulationMark":"D","legal":{"standard":true,"expanded":true}}