{"id":"ex15-12","localId":"12","name":"Typhlosion δ","image":"https://assets.tcgdex.net/en/ex/ex15/12","illustrator":"Hisao Nakamura","rarity":"Rare","category":"Pokemon","variants":{"normal":true,"reverse":true,"holo":true,"firstEdition":false},"set":{"id":"ex15","logo":"https://assets.tcgdex.net/en/ex/ex15/logo","symbol":"https://assets.tcgdex.net/univ/ex/ex15/symbol","name":"Dragon Frontiers","cardCount":{"total":101,"official":101}},"dexId":[157],"hp":100,"types":["Psychic"],"evolveFrom":"Quilava","stage":"Stage2","abilities":[{"type":"Poke-POWER","name":"Shady Move","effect":"Once during your turn (before your attack), if Typhlosion is your Active Pokémon, you may move 1 damage counter from either player's Pokémon to another Pokémon (yours or your opponent's). This power can't be used if Typhlosion is affected by a Special Condition."}],"attacks":[{"cost":["Psychic","Colorless","Colorless"],"name":"Burning Ball","effect":"If Typhlosion has at least 2 Fire Energy attached to it, the Defending Pokémon is now Burned.","damage":60}],"weaknesses":[{"type":"Water","value":"×2"}]}