{"id":"xy7-22","localId":22,"dexId":134,"name":"Aquali","hp":90,"type":[{"id":10,"name":"Eau"}],"image":{"low":"https://assets.tcgdex.net/fr/xy/xy7/22/low","high":"https://assets.tcgdex.net/fr/xy/xy7/22/high"},"evolveFrom":"Évoli","tags":[{"id":14,"name":"Niveau 1"}],"illustrator":{"id":47,"name":"kirisAki"},"abilities":[{"name":"Effet Aqua","text":"Chacun de vos Pokémon de Niveau 1 en jeu est maintenant un Pokémon Water en plus de ses types existants.","type":{"id":2,"name":"Talent"}}],"attacks":[{"name":"Hydro-Éclaboussure","cost":["Eau","Incolore","Incolore"],"damage":70}],"weaknesses":[{"type":{"id":6,"name":"Plante"},"value":"×2"}],"retreat":2,"rarity":{"id":1,"name":"Non Commun"},"category":{"id":0,"name":"Pokémon"},"set":{"name":"Ancient Origins","code":"xy7"}}