{"category":"Pokemon","id":"smp-SM06","illustrator":"match","localId":"SM06","name":"Wuffels","rarity":"Rare","set":{"cardCount":{"official":236,"total":236},"id":"smp","name":"SM Promokarten","symbol":"https://assets.tcgdex.net/univ/sm/smp/symbol"},"variants":{"firstEdition":false,"holo":false,"normal":true,"reverse":true},"dexId":[744],"hp":60,"types":["Fighting"],"stage":"Basic","attacks":[{"cost":["Colorless"],"name":"Tackle","damage":10},{"cost":["Fighting","Colorless"],"name":"Steinwurf","damage":20}],"weaknesses":[{"type":"Grass","value":"×2"}],"retreat":1,"legal":{"standard":true,"expanded":true}}