{"id":"xy11-30","localId":"30","name":"Moustillon","image":"https://assets.tcgdex.net/fr/xy/xy11/30","illustrator":"sui","rarity":"Commune","category":"Pokémon","variants":{"normal":true,"reverse":true,"holo":true,"firstEdition":false},"set":{"id":"xy11","name":"Offensive Vapeur","cardCount":{"total":116,"official":114}},"dexId":[501],"hp":60,"types":["Eau"],"stage":"Base","attacks":[{"cost":["Eau","Incolore"],"name":"Pistolet à O","damage":30}],"weaknesses":[{"type":"Plante","value":"×2"}],"retreat":1}