{"id":"xy4-7","localId":"7","name":"Manternel","image":"https://assets.tcgdex.net/fr/xy/xy4/7","illustrator":"Atsuko Nishida","rarity":"Rare","category":"Pokémon","variants":{"normal":true,"reverse":true,"holo":false,"firstEdition":false},"set":{"id":"xy4","name":"Vigueur Spectrale","cardCount":{"total":122,"official":119}},"dexId":[542],"hp":130,"types":["Plante"],"evolveFrom":"Couverdure","stage":"Biveau2","attacks":[{"cost":["Plante"],"name":"Composition","effect":"Choisissez jusqu'à 2 de vos Pokémon de Banc qui n'ont pas de carte Outil Pokémon leur étant attachée. Pour chacun des Pokémon choisis, cherchez une carte Outil Pokémon dans votre deck et attachez-la au Pokémon. Mélangez ensuite votre deck."},{"cost":["Plante","Plante","Incolore"],"name":"Tempête Verte","effect":"Soignez 20 dégâts à chacun de vos Pokémon Grass.","damage":70}],"weaknesses":[{"type":"Feu","value":"×2"}],"retreat":1}