{"name":"Unseen Forces Unown Collection","id":"exu","serie":{"id":"ex","name":"EX"},"cardCount":{"total":28,"official":28},"releaseDate":"2005-08-22","legal":{"standard":false,"expanded":false},"cards":[{"id":"exu-!","localId":"!","name":"Unown"},{"id":"exu-%3F","localId":"%3F","name":"Unown"},{"id":"exu-A","localId":"A","name":"Unown"},{"id":"exu-B","localId":"B","name":"Unown"},{"id":"exu-C","localId":"C","name":"Unown"},{"id":"exu-D","localId":"D","name":"Unown"},{"id":"exu-E","localId":"E","name":"Unown"},{"id":"exu-F","localId":"F","name":"Unown"},{"id":"exu-G","localId":"G","name":"Unown"},{"id":"exu-H","localId":"H","name":"Unown"},{"id":"exu-I","localId":"I","name":"Unown"},{"id":"exu-J","localId":"J","name":"Unown"},{"id":"exu-K","localId":"K","name":"Unown"},{"id":"exu-L","localId":"L","name":"Unown"},{"id":"exu-M","localId":"M","name":"Unown"},{"id":"exu-N","localId":"N","name":"Unown"},{"id":"exu-O","localId":"O","name":"Unown"},{"id":"exu-P","localId":"P","name":"Unown"},{"id":"exu-Q","localId":"Q","name":"Unown"},{"id":"exu-R","localId":"R","name":"Unown"},{"id":"exu-S","localId":"S","name":"Unown"},{"id":"exu-T","localId":"T","name":"Unown"},{"id":"exu-U","localId":"U","name":"Unown"},{"id":"exu-V","localId":"V","name":"Unown"},{"id":"exu-W","localId":"W","name":"Unown"},{"id":"exu-X","localId":"X","name":"Unown"},{"id":"exu-Y","localId":"Y","name":"Unown"},{"id":"exu-Z","localId":"Z","name":"Unown"}]}