{"id":"sm12-104","localId":"104","name":"Blacephalon","image":"https://assets.tcgdex.net/en/sm/sm12/104","illustrator":"Hasuno","rarity":"Rare","category":"Pokemon","variants":{"normal":true,"reverse":true,"holo":true,"firstEdition":false},"set":{"id":"sm12","name":"Cosmic Eclipse","cardCount":{"total":271,"official":236}},"dexId":[806],"hp":110,"types":["Psychic"],"stage":"Basic","attacks":[{"cost":["Psychic","Colorless"],"name":"Fireworks Bomb","effect":"Put 4 damage counters on your opponent's Pokémon in any way you like. If your opponent has exactly 3 Prize cards remaining, put 12 damage counters on them instead."}],"weaknesses":[{"type":"Darkness","value":"×2"}],"resistances":[{"type":"Fightning","value":"-20"}],"retreat":2}