{"category":"Pokemon","id":"sm1-67","illustrator":"Mina Nakai","localId":"67","name":"Makuhita","rarity":"Common","set":{"cardCount":{"official":149,"total":163},"id":"sm1","symbol":"https://assets.tcgdex.net/univ/sm/sm1/symbol"},"variants":{"firstEdition":false,"holo":false,"normal":true,"reverse":true},"dexId":[296],"hp":80,"types":["Fighting"],"stage":"Basic","attacks":[{"cost":["Fighting"],"name":"Überraschungsangriff","effect":"Wirf 1 Münze. Bei Zahl hat diese Attacke keine Auswirkungen.","damage":20},{"cost":["Fighting","Colorless"],"name":"Stärke","damage":40}],"weaknesses":[{"type":"Psychic","value":"×2"}],"retreat":2,"legal":{"standard":true,"expanded":true}}