{"id":"swsh1-187","localId":"187","name":"Sinistrail V","image":"https://assets.tcgdex.net/fr/swsh/swsh1/187","illustrator":"Eske Yoshinob","rarity":"Ultra Rare","category":"Pokémon","variants":{"normal":true,"reverse":true,"holo":false,"firstEdition":false},"set":{"id":"swsh1","logo":"https://assets.tcgdex.net/fr/swsh/swsh1/logo","symbol":"https://assets.tcgdex.net/univ/swsh/swsh1/symbol","name":"Épée et Bouclier","cardCount":{"total":216,"official":202}},"hp":220,"types":["Plante"],"suffix":"V","attacks":[{"cost":["Plante"],"name":"Colère Ancrée","effect":"Si l’un de vos Pokémon Grass a été mis K.O. par les dégâts d’une attaque de votre adversaire lors de son dernier tour, cette attaque inflige 90 dégâts supplémentaires.","damage":"30+"},{"cost":["Plante","Plante","Incolore"],"name":"Giga Marteau","effect":"Pendant votre prochain tour, ce Pokémon ne peut pas utiliser Giga Marteau.","damage":200}],"weaknesses":[{"type":"Feu","value":"×2"}],"retreat":2,"regulationMark":"D","legal":{"standard":true,"expanded":true}}