{"id":"xy8-86","localId":"86","name":"Pandespiègle","illustrator":"Mizue","rarity":"Commune","category":"Pokémon","variants":{"normal":true,"reverse":true,"holo":true,"firstEdition":false},"set":{"id":"xy8","name":"Impulsion Turbo","cardCount":{"total":164,"official":162}},"dexId":[674],"hp":60,"types":["Combat"],"stage":"Base","attacks":[{"cost":["Combat","Incolore"],"name":"Coup d'Poing Solennel","effect":"Défaussez au hasard une carte de la main de votre adversaire.","damage":10}],"weaknesses":[{"type":"Psy","value":"×2"}],"retreat":2}