{"category":"Pokemon","id":"smp-SM22","illustrator":"5ban Graphics","image":"https://assets.tcgdex.net/en/sm/smp/SM22","localId":"SM22","name":"Rowlet","rarity":"Common","set":{"cardCount":{"official":236,"total":236},"id":"smp","logo":"https://assets.tcgdex.net/en/sm/smp/logo","name":"SM Black Star Promos","symbol":"https://assets.tcgdex.net/univ/sm/smp/symbol"},"variants":{"firstEdition":false,"holo":false,"normal":true,"reverse":true},"dexId":[722],"hp":60,"types":["Grass"],"stage":"Basic","attacks":[{"cost":["Colorless"],"name":"Tackle","damage":10},{"cost":["Grass","Colorless"],"name":"Leafage","damage":20}],"weaknesses":[{"type":"Fire","value":"×2"}],"legal":{"standard":true,"expanded":true}}