{"id":"xy5-111","localId":"111","name":"Zigzaton","image":"https://assets.tcgdex.net/fr/xy/xy5/111","illustrator":"Sumiyoshi Kizuki","rarity":"Commune","category":"Pokémon","variants":{"normal":true,"reverse":true,"holo":false,"firstEdition":false},"set":{"id":"xy5","name":"Primo-Choc","cardCount":{"total":164,"official":160}},"dexId":[263],"hp":60,"types":["Incolore"],"stage":"Base","attacks":[{"cost":["Incolore"],"name":"Jet de Sable","effect":"Si le Pokémon Défenseur essaie d'attaquer pendant le prochain tour de votre adversaire, ce dernier lance une pièce. Si c’est pile, son attaque ne fait rien."},{"cost":["Incolore","Incolore"],"name":"Coup d'Boule","damage":20}],"weaknesses":[{"type":"Combat","value":"×2"}],"retreat":1}