{"category":"Pokémon","id":"swsh4.5-52","illustrator":"so-taro","image":"https://assets.tcgdex.net/fr/swsh/swsh4.5/52","localId":"52","name":"Évoli","rarity":"Commune","set":{"cardCount":{"official":72,"total":195},"id":"swsh4.5","logo":"https://assets.tcgdex.net/fr/swsh/swsh4.5/logo","name":"Déstinées Radieuses","symbol":"https://assets.tcgdex.net/univ/swsh/swsh4.5/symbol"},"variants":{"firstEdition":false,"holo":false,"normal":true,"reverse":false},"hp":60,"types":["Incolore"],"attacks":[{"cost":["Incolore"],"name":"Signes d’Évolution","effect":"Cherchez dans votre deck une carte Évolution d’Évoli, montrez-la, puis ajoutez-la à votre main. Mélangez ensuite votre deck."},{"cost":["Incolore","Incolore"],"name":"Coup Déchaîné","effect":"Lancez une pièce. Si c’est pile, cette attaque ne fait rien.","damage":30}],"weaknesses":[{"type":"Combat","value":"×2"}],"retreat":1,"regulationMark":"D","legal":{"standard":true,"expanded":true}}